kmlb/__init__.py
kmlb/base.py
kmlb/gis_basics.py
kmlb/shapes.py
kmlb-0.0.94.dist-info/LICENSE.md
kmlb-0.0.94.dist-info/METADATA
kmlb-0.0.94.dist-info/WHEEL
kmlb-0.0.94.dist-info/top_level.txt
kmlb-0.0.94.dist-info/RECORD
