Metadata-Version: 2.1
Name: kmlb
Version: 0.0.94
Summary: A Straightforward Google Earth KML Builder
Home-page: https://github.com/HFM3/kmlb
Author: HFM3
Classifier: Programming Language :: Python :: 3.8
Classifier: License :: OSI Approved :: GNU General Public License v3 (GPLv3)
Classifier: Operating System :: OS Independent
Classifier: Intended Audience :: Science/Research
Requires-Python: >=3.8
License-File: LICENSE.md
